my_package/__init__.py
my_package/model_interafce.py
my_package/utils.py
tests/__init__.py
tests/test_model_interface.py
llm_unified_interface-0.1.dist-info/METADATA
llm_unified_interface-0.1.dist-info/WHEEL
llm_unified_interface-0.1.dist-info/top_level.txt
llm_unified_interface-0.1.dist-info/RECORD
